unkchan/__init__.py
unkchan/unk.py
unkchan-1.0.0.dist-info/LICENSE
unkchan-1.0.0.dist-info/METADATA
unkchan-1.0.0.dist-info/WHEEL
unkchan-1.0.0.dist-info/top_level.txt
unkchan-1.0.0.dist-info/RECORD
