Metadata-Version: 2.1
Name: unkchan
Version: 1.0.0
Summary: I love unkchan, you can get his words.
Home-page: https://github.com/nakajiii/unkchan
Author: nakajiii
Author-email: tdic.lctw@gmail.com
License: MIT
Keywords: unkchan nakajiii
Platform: UNKNOWN
Classifier: License :: OSI Approved :: MIT License
Classifier: Programming Language :: Python :: 3.6
